MANIFEST.in
README.rst
magicmemoryview.c
magicmemoryview.pyx
setup.py
magicmemoryview.egg-info/PKG-INFO
magicmemoryview.egg-info/SOURCES.txt
magicmemoryview.egg-info/dependency_links.txt
magicmemoryview.egg-info/top_level.txt