Metadata-Version: 1.1
Name: magicmemoryview
Version: 0.1.5
Summary: Magic memoryview() style casting for Cython
Home-page: http://github.com/cuspaceflight/magicmemoryview
Author: Cambridge University Spaceflight
Author-email: contact@cusf.co.uk
License: GPLv3+
Platform: UNKNOWN
Classifier: Development Status :: 4 - Beta
Classifier: License :: OSI Approved :: GNU General Public License v3 or later (GPLv3+)
Classifier: Programming Language :: Python :: 3.3
